pyquerytracker/__init__.py
pyquerytracker/config.py
pyquerytracker/core.py
pyquerytracker-0.1.0.dist-info/licenses/LICENSE
pyquerytracker-0.1.0.dist-info/METADATA
pyquerytracker-0.1.0.dist-info/WHEEL
pyquerytracker-0.1.0.dist-info/top_level.txt
pyquerytracker-0.1.0.dist-info/RECORD
