Metadata-Version: 2.4
Name: pyquerytracker
Version: 0.1.0
Summary: A lightweight, decorator-based query performance tracking library for Python applications. Monitor and analyze database query performance with ease.
Author-email: MuddyHope <daktarisun@gmail.com>
License: MIT
Project-URL: Repository, https://github.com/MuddyHope/pyquerytracker
Project-URL: Issues, https://github.com/MuddyHope/pyquerytracker/issues
Keywords: performance,database,query,decorator,tracking
Classifier: Development Status :: 3 - Alpha
Classifier: Intended Audience :: Developers
Classifier: License :: OSI Approved :: MIT License
Classifier: Programming Language :: Python :: 3
Classifier: Programming Language :: Python :: 3.11
Classifier: Programming Language :: Python :: 3.12
Classifier: Programming Language :: Python :: 3.13
Classifier: Topic :: Software Development :: Libraries :: Python Modules
Requires-Python: >=3.11
License-File: LICENSE
Dynamic: license-file
